vtmon/__init__.py
vtmon/__main__.py
vtmon-1.1.0.dist-info/entry_points.txt
vtmon-1.1.0.dist-info/WHEEL
vtmon-1.1.0.dist-info/METADATA
vtmon-1.1.0.dist-info/RECORD
