Metadata-Version: 2.1
Name: vtmon
Version: 1.1.0
Summary: Get a notification when any hash from a list of hashes is publicly uploaded to VirusTotal
Author-email: Frederik Reiter <vtmon@frereit.de>
Requires-Python: >=3.11.2
Classifier: Development Status :: 5 - Production/Stable
Classifier: Intended Audience :: Information Technology
Classifier: License :: OSI Approved :: MIT License
Classifier: Programming Language :: Python :: 3 :: Only
Classifier: Programming Language :: Python :: 3.11
Classifier: Programming Language :: Python :: 3.12
Requires-Dist: apprise~=1.8.0
Requires-Dist: requests~=2.32.3
Requires-Dist: vt-py~=0.18.2
Requires-Dist: black~=24.4.2 ; extra == "dev"
Provides-Extra: dev
